detensor_cli/__init__.py
detensor_cli/__main__.py
detensor_cli/consts.py
detensor_cli/detensor_cli.py
detensor_cli/exceptions.py
detensor_cli/extensions.py
detensor_cli/i18n.py
detensor_cli/py.typed
detensor_cli/cli/__init__.py
detensor_cli/cli/customize.py
detensor_cli/cli/utils.py
detensor_cli/cli/commands/__init__.py
detensor_cli/cli/commands/driver.py
detensor_cli/cli/commands/exec.py
detensor_cli/cli/commands/pro_project.py
detensor_cli/cli/commands/project.py
detensor_cli/cli/commands/self.py
detensor_cli/cli/commands/test_multi_node.py
detensor_cli/config/__init__.py
detensor_cli/config/model.py
detensor_cli/config/parser.py
detensor_cli/handlers/__init__.py
detensor_cli/handlers/data.py
detensor_cli/handlers/meta.py
detensor_cli/handlers/pip.py
detensor_cli/handlers/process.py
detensor_cli/handlers/project.py
detensor_cli/handlers/reloader.py
detensor_cli/handlers/script.py
detensor_cli/handlers/signal.py
detensor_cli/handlers/store.py
detensor_cli/handlers/venv.py
detensor_cli/locale/__init__.py
detensor_cli/log/__init__.py
detensor_cli/template/__init__.py
detensor_cli-0.1.3.dist-info/AUTHORS.rst
detensor_cli-0.1.3.dist-info/LICENSE
detensor_cli-0.1.3.dist-info/METADATA
detensor_cli-0.1.3.dist-info/WHEEL
detensor_cli-0.1.3.dist-info/entry_points.txt
detensor_cli-0.1.3.dist-info/top_level.txt
detensor_cli-0.1.3.dist-info/RECORD
