Metadata-Version: 2.1
Name: detensor_cli
Version: 0.1.3
Summary: a cli tool for detensor
Home-page: https://github.com/tjr20202021@163.com/detensor_cli
Author: buaatjr
Author-email: tjr20202021@163.com
License: MIT license
Keywords: detensor_cli
Classifier: Development Status :: 2 - Pre-Alpha
Classifier: Intended Audience :: Developers
Classifier: License :: OSI Approved :: MIT License
Classifier: Natural Language :: English
Classifier: Programming Language :: Python :: 3
Classifier: Programming Language :: Python :: 3.10
Requires-Python: >=3.10
License-File: LICENSE
License-File: AUTHORS.rst
Requires-Dist: Click >=7.0
